{
  "last_updated": "2025-12-20T01:58:14.646072+00:00",
  "packages": {
    "torch": {
      "version": "2.9.1",
      "last_updated": "2025-12-20T01:58:14.715470+00:00"
    },
    "numpy": {
      "version": "2.3.5",
      "last_updated": "2025-12-20T01:58:14.922971+00:00"
    },
    "pandas": {
      "version": "2.3.3",
      "last_updated": "2025-12-20T01:58:15.107168+00:00"
    },
    "requests": {
      "version": "2.32.5",
      "last_updated": "2025-12-20T01:58:15.260828+00:00"
    },
    "django": {
      "version": "6.0",
      "last_updated": "2025-12-20T01:58:15.420753+00:00"
    },
    "flask": {
      "version": "3.1.2",
      "last_updated": "2025-12-20T01:58:15.569449+00:00"
    },
    "tensorflow": {
      "version": "2.20.0",
      "last_updated": "2025-12-20T01:58:15.744968+00:00"
    },
    "scikit-learn": {
      "version": "1.8.0",
      "last_updated": "2025-12-20T01:58:15.918919+00:00"
    },
    "matplotlib": {
      "version": "3.10.8",
      "last_updated": "2025-12-20T01:58:16.109305+00:00"
    },
    "scipy": {
      "version": "1.16.3",
      "last_updated": "2025-12-20T01:58:16.360116+00:00"
    },
    "opencv-python": {
      "version": "4.12.0.88",
      "last_updated": "2025-12-20T01:58:16.559372+00:00"
    },
    "pillow": {
      "version": "12.0.0",
      "last_updated": "2025-12-20T01:58:16.832004+00:00"
    },
    "pytest": {
      "version": "9.0.2",
      "last_updated": "2025-12-20T01:58:16.989333+00:00"
    },
    "black": {
      "version": "25.12.0",
      "last_updated": "2025-12-20T01:58:17.253487+00:00"
    },
    "mypy": {
      "version": "1.19.1",
      "last_updated": "2025-12-20T01:58:17.456171+00:00"
    },
    "pylint": {
      "version": "4.0.4",
      "last_updated": "2025-12-20T01:58:17.628445+00:00"
    },
    "setuptools": {
      "version": "80.9.0",
      "last_updated": "2025-12-20T01:58:17.798967+00:00"
    },
    "wheel": {
      "version": "0.45.1",
      "last_updated": "2025-12-20T01:58:17.948659+00:00"
    },
    "pip": {
      "version": "25.3",
      "last_updated": "2025-12-20T01:58:18.104696+00:00"
    },
    "cryptography": {
      "version": "46.0.3",
      "last_updated": "2025-12-20T01:58:18.298885+00:00"
    },
    "sqlalchemy": {
      "version": "2.0.45",
      "last_updated": "2025-12-20T01:58:18.522911+00:00"
    },
    "pydantic": {
      "version": "2.12.5",
      "last_updated": "2025-12-20T01:58:18.703383+00:00"
    },
    "fastapi": {
      "version": "0.125.0",
      "last_updated": "2025-12-20T01:58:18.863560+00:00"
    },
    "uvicorn": {
      "version": "0.38.0",
      "last_updated": "2025-12-20T01:58:19.025989+00:00"
    },
    "httpx": {
      "version": "0.28.1",
      "last_updated": "2025-12-20T01:58:19.176904+00:00"
    },
    "aiohttp": {
      "version": "3.13.2",
      "last_updated": "2025-12-20T01:58:19.457612+00:00"
    },
    "beautifulsoup4": {
      "version": "4.14.3",
      "last_updated": "2025-12-20T01:58:19.613138+00:00"
    },
    "lxml": {
      "version": "6.0.2",
      "last_updated": "2025-12-20T01:58:19.843133+00:00"
    },
    "click": {
      "version": "8.3.1",
      "last_updated": "2025-12-20T01:58:19.992829+00:00"
    },
    "typer": {
      "version": "0.20.1",
      "last_updated": "2025-12-20T01:58:20.143666+00:00"
    },
    "rich": {
      "version": "14.2.0",
      "last_updated": "2025-12-20T01:58:20.303406+00:00"
    },
    "tqdm": {
      "version": "4.67.1",
      "last_updated": "2025-12-20T01:58:20.460277+00:00"
    },
    "jinja2": {
      "version": "3.1.6",
      "last_updated": "2025-12-20T01:58:20.607694+00:00"
    }
  },
  "total_packages": 33
}