{
  "package": "azure-core",
  "last_updated": "1.38.2",
  "python_compatibility": {
    "3.7": {
      "version": "1.30.1",
      "released": "2024-02-29T21:06:11"
    },
    "3.8": {
      "version": "1.33.0",
      "released": "2025-04-03T23:51:03"
    },
    "3.9": {
      "version": "1.38.2",
      "released": "2026-02-18T19:33:07"
    },
    "3.10": {
      "version": "1.38.2",
      "released": "2026-02-18T19:33:07"
    },
    "3.11": {
      "version": "1.38.2",
      "released": "2026-02-18T19:33:07"
    },
    "3.12": {
      "version": "1.38.2",
      "released": "2026-02-18T19:33:07"
    },
    "3.13": {
      "version": "1.38.2",
      "released": "2026-02-18T19:33:07"
    },
    "3.14": {
      "version": "1.38.2",
      "released": "2026-02-18T19:33:07"
    }
  }
}